sxc_api_client/__init__.py
sxc_api_client/client.py
sxc_api_client/constants.py
sxc_api_client/exceptions.py
sxc_api_client/request_params.py
sxc_api_client-0.1.9.dist-info/METADATA
sxc_api_client-0.1.9.dist-info/WHEEL
sxc_api_client-0.1.9.dist-info/licenses/LICENSE
sxc_api_client-0.1.9.dist-info/RECORD
