Metadata-Version: 2.1
Name: sxc-api-client
Version: 0.1.9
Summary: SouthXChange API Client
Project-URL: Homepage, https://github.com/amid-flice/sxc-api-client
Project-URL: Bug Tracker, https://github.com/amid-flice/sxc-api-client/issues
Author-email: Dmitry Kosilov <amidflice@gmail.com>
License-File: LICENSE
Keywords: api client,crypto,cryptocurrency,exchange,southxchange,trading
Classifier: License :: OSI Approved :: MIT License
Classifier: Operating System :: OS Independent
Classifier: Programming Language :: Python :: 3
Requires-Python: >=3.10
Requires-Dist: requests>=2.28.1
Requires-Dist: strenum>=0.4.8
